pxsol/__init__.py
pxsol/base58.py
pxsol/bincode.py
pxsol/borsh.py
pxsol/compact_u16.py
pxsol/config.py
pxsol/core.py
pxsol/denomination.py
pxsol/ed25519.py
pxsol/eddsa.py
pxsol/io.py
pxsol/log.py
pxsol/objectdict.py
pxsol/program.py
pxsol/rate.py
pxsol/rpc.py
pxsol/wallet.py
pxsol-1.1.5.dist-info/METADATA
pxsol-1.1.5.dist-info/WHEEL
pxsol-1.1.5.dist-info/licenses/LICENSE
pxsol-1.1.5.dist-info/RECORD
