Metadata-Version: 2.4
Name: pxsol
Version: 1.1.5
Summary: Pxsol: solana library for humans
Project-URL: homepage, https://github.com/libraries/pxsol
Author-email: Mohanson <mohanson@outlook.com>
License: MIT License
License-File: LICENSE
Requires-Python: >=3.14
Requires-Dist: requests
